phase2_rtl_foundation/alu.v
// Basic ALU for RISC-V CPU
// Supports fundamental arithmetic and logic operations
// 32-bit operands to match RISC-V architecture

module alu (
    input  [31:0] a,           // First operand
    input  [31:0] b,           // Second operand
    input  [3:0]  alu_op,      // ALU operation selector
    output reg [31:0] result,  // ALU result
    output zero,               // Zero flag (result == 0)
    output overflow,           // Overflow flag for signed operations
    output carry               // Carry flag for unsigned operations
);

    // ALU operation codes
    localparam ALU_ADD  = 4'b0000;  // Addition
    localparam ALU_SUB  = 4'b0001;  // Subtraction
    localparam ALU_AND  = 4'b0010;  // Bitwise AND
    localparam ALU_OR   = 4'b0011;  // Bitwise OR
    localparam ALU_XOR  = 4'b0100;  // Bitwise XOR
    localparam ALU_SLT  = 4'b0101;  // Set Less Than (signed)
    localparam ALU_SLTU = 4'b0110;  // Set Less Than Unsigned
    localparam ALU_SLL  = 4'b0111;  // Shift Left Logical
    localparam ALU_SRL  = 4'b1000;  // Shift Right Logical
    localparam ALU_SRA  = 4'b1001;  // Shift Right Arithmetic

    // Internal signals for flag generation
    wire [32:0] add_result;     // 33-bit for carry detection
    wire [32:0] sub_result;     // 33-bit for borrow detection
    wire        a_sign, b_sign, result_sign;
    
    // Extended addition and subtraction for flag calculation
    assign add_result = {1'b0, a} + {1'b0, b};
    assign sub_result = {1'b0, a} - {1'b0, b};
    
    // Sign bits for overflow detection
    assign a_sign = a[31];
    assign b_sign = b[31];
    assign result_sign = result[31];

    // Main ALU logic
    always @(*) begin
        case (alu_op)
            ALU_ADD:  result = a + b;
            ALU_SUB:  result = a - b;
            ALU_AND:  result = a & b;
            ALU_OR:   result = a | b;
            ALU_XOR:  result = a ^ b;
            ALU_SLT:  result = ($signed(a) < $signed(b)) ? 32'h1 : 32'h0;
            ALU_SLTU: result = (a < b) ? 32'h1 : 32'h0;
            ALU_SLL:  result = a << b[4:0];  // Only use lower 5 bits for shift amount
            ALU_SRL:  result = a >> b[4:0];
            ALU_SRA:  result = $signed(a) >>> b[4:0];  // Arithmetic right shift
            default:  result = 32'h0;
        endcase
    end

    // Flag generation
    assign zero = (result == 32'h0);
    
    // Carry flag: set for unsigned overflow in addition or underflow in subtraction
    assign carry = (alu_op == ALU_ADD) ? add_result[32] :
                   (alu_op == ALU_SUB) ? sub_result[32] : 1'b0;
    
    // Overflow flag: set for signed overflow in addition or subtraction
    assign overflow = (alu_op == ALU_ADD) ? (a_sign == b_sign) && (result_sign != a_sign) :
                      (alu_op == ALU_SUB) ? (a_sign != b_sign) && (result_sign != a_sign) : 1'b0;

endmodule

testbenches/tb_alu.v
// Testbench for ALU module
// Comprehensive testing of all ALU operations and flag generation

`timescale 1ns/1ps

module tb_alu;

    // Testbench signals
    reg  [31:0] a, b;
    reg  [3:0]  alu_op;
    wire [31:0] result;
    wire zero, overflow, carry;
    
    // Test result tracking
    integer test_count = 0;
    integer pass_count = 0;
    
    // Instantiate ALU
    alu dut (
        .a(a),
        .b(b),
        .alu_op(alu_op),
        .result(result),
        .zero(zero),
        .overflow(overflow),
        .carry(carry)
    );
    
    // ALU operation codes (matching the module)
    localparam ALU_ADD  = 4'b0000;
    localparam ALU_SUB  = 4'b0001;
    localparam ALU_AND  = 4'b0010;
    localparam ALU_OR   = 4'b0011;
    localparam ALU_XOR  = 4'b0100;
    localparam ALU_SLT  = 4'b0101;
    localparam ALU_SLTU = 4'b0110;
    localparam ALU_SLL  = 4'b0111;
    localparam ALU_SRL  = 4'b1000;
    localparam ALU_SRA  = 4'b1001;
    
    // Task to check ALU result
    task check_result;
        input [31:0] expected_result;
        input expected_zero;
        input expected_overflow;
        input expected_carry;
        input [8*20:1] test_name;
        begin
            test_count = test_count + 1;
            #1; // Small delay for signals to settle
            
            if (result === expected_result && 
                zero === expected_zero && 
                overflow === expected_overflow && 
                carry === expected_carry) begin
                $display("✅ PASS: %s", test_name);
                $display("   A=%h, B=%h, Op=%b -> Result=%h, Z=%b, V=%b, C=%b", 
                         a, b, alu_op, result, zero, overflow, carry);
                pass_count = pass_count + 1;
            end else begin
                $display("❌ FAIL: %s", test_name);
                $display("   A=%h, B=%h, Op=%b", a, b, alu_op);
                $display("   Expected: Result=%h, Z=%b, V=%b, C=%b", 
                         expected_result, expected_zero, expected_overflow, expected_carry);
                $display("   Got:      Result=%h, Z=%b, V=%b, C=%b", 
                         result, zero, overflow, carry);
            end
            $display("");
        end
    endtask
    
    // Main test sequence
    initial begin
        $display("=== ALU Testbench Starting ===");
        $display("");
        
        // Test Addition
        $display("--- Testing Addition ---");
        a = 32'h00000005; b = 32'h00000003; alu_op = ALU_ADD;
        check_result(32'h00000008, 1'b0, 1'b0, 1'b0, "ADD: 5 + 3 = 8");
        
        a = 32'hFFFFFFFF; b = 32'h00000001; alu_op = ALU_ADD;
        check_result(32'h00000000, 1'b1, 1'b0, 1'b1, "ADD: -1 + 1 = 0 (carry)");
        
        a = 32'h7FFFFFFF; b = 32'h00000001; alu_op = ALU_ADD;
        check_result(32'h80000000, 1'b0, 1'b1, 1'b0, "ADD: overflow test");
        
        // Test Subtraction
        $display("--- Testing Subtraction ---");
        a = 32'h00000008; b = 32'h00000003; alu_op = ALU_SUB;
        check_result(32'h00000005, 1'b0, 1'b0, 1'b0, "SUB: 8 - 3 = 5");
        
        a = 32'h00000003; b = 32'h00000008; alu_op = ALU_SUB;
        check_result(32'hFFFFFFFB, 1'b0, 1'b0, 1'b1, "SUB: 3 - 8 = -5 (borrow)");
        
        a = 32'h80000000; b = 32'h00000001; alu_op = ALU_SUB;
        check_result(32'h7FFFFFFF, 1'b0, 1'b1, 1'b0, "SUB: overflow test");
        
        // Test Bitwise AND
        $display("--- Testing Bitwise AND ---");
        a = 32'hF0F0F0F0; b = 32'h0F0F0F0F; alu_op = ALU_AND;
        check_result(32'h00000000, 1'b1, 1'b0, 1'b0, "AND: F0F0F0F0 & 0F0F0F0F");
        
        a = 32'hFFFFFFFF; b = 32'h12345678; alu_op = ALU_AND;
        check_result(32'h12345678, 1'b0, 1'b0, 1'b0, "AND: FFFFFFFF & 12345678");
        
        // Test Bitwise OR
        $display("--- Testing Bitwise OR ---");
        a = 32'hF0F0F0F0; b = 32'h0F0F0F0F; alu_op = ALU_OR;
        check_result(32'hFFFFFFFF, 1'b0, 1'b0, 1'b0, "OR: F0F0F0F0 | 0F0F0F0F");
        
        a = 32'h00000000; b = 32'h00000000; alu_op = ALU_OR;
        check_result(32'h00000000, 1'b1, 1'b0, 1'b0, "OR: 0 | 0 = 0");
        
        // Test Bitwise XOR
        $display("--- Testing Bitwise XOR ---");
        a = 32'hF0F0F0F0; b = 32'h0F0F0F0F; alu_op = ALU_XOR;
        check_result(32'hFFFFFFFF, 1'b0, 1'b0, 1'b0, "XOR: F0F0F0F0 ^ 0F0F0F0F");
        
        a = 32'h12345678; b = 32'h12345678; alu_op = ALU_XOR;
        check_result(32'h00000000, 1'b1, 1'b0, 1'b0, "XOR: same values = 0");
        
        // Test Set Less Than (signed)
        $display("--- Testing Set Less Than (Signed) ---");
        a = 32'h00000005; b = 32'h00000008; alu_op = ALU_SLT;
        check_result(32'h00000001, 1'b0, 1'b0, 1'b0, "SLT: 5 < 8 = true");
        
        a = 32'h00000008; b = 32'h00000005; alu_op = ALU_SLT;
        check_result(32'h00000000, 1'b1, 1'b0, 1'b0, "SLT: 8 < 5 = false");
        
        a = 32'hFFFFFFFF; b = 32'h00000001; alu_op = ALU_SLT;
        check_result(32'h00000001, 1'b0, 1'b0, 1'b0, "SLT: -1 < 1 = true");
        
        // Test Set Less Than Unsigned
        $display("--- Testing Set Less Than (Unsigned) ---");
        a = 32'hFFFFFFFF; b = 32'h00000001; alu_op = ALU_SLTU;
        check_result(32'h00000000, 1'b1, 1'b0, 1'b0, "SLTU: 0xFFFFFFFF < 1 = false");
        
        a = 32'h00000001; b = 32'hFFFFFFFF; alu_op = ALU_SLTU;
        check_result(32'h00000001, 1'b0, 1'b0, 1'b0, "SLTU: 1 < 0xFFFFFFFF = true");
        
        // Test Shift Left Logical
        $display("--- Testing Shift Left Logical ---");
        a = 32'h00000001; b = 32'h00000004; alu_op = ALU_SLL;
        check_result(32'h00000010, 1'b0, 1'b0, 1'b0, "SLL: 1 << 4 = 16");
        
        a = 32'h12345678; b = 32'h00000008; alu_op = ALU_SLL;
        check_result(32'h34567800, 1'b0, 1'b0, 1'b0, "SLL: 0x12345678 << 8");
        
        // Test Shift Right Logical
        $display("--- Testing Shift Right Logical ---");
        a = 32'h00000010; b = 32'h00000004; alu_op = ALU_SRL;
        check_result(32'h00000001, 1'b0, 1'b0, 1'b0, "SRL: 16 >> 4 = 1");
        
        a = 32'h80000000; b = 32'h00000001; alu_op = ALU_SRL;
        check_result(32'h40000000, 1'b0, 1'b0, 1'b0, "SRL: 0x80000000 >> 1");
        
        // Test Shift Right Arithmetic
        $display("--- Testing Shift Right Arithmetic ---");
        a = 32'h80000000; b = 32'h00000001; alu_op = ALU_SRA;
        check_result(32'hC0000000, 1'b0, 1'b0, 1'b0, "SRA: 0x80000000 >>> 1 (sign extend)");
        
        a = 32'h40000000; b = 32'h00000001; alu_op = ALU_SRA;
        check_result(32'h20000000, 1'b0, 1'b0, 1'b0, "SRA: 0x40000000 >>> 1");
        
        // Test Summary
        $display("=== ALU Test Summary ===");
        $display("Total tests: %0d", test_count);
        $display("Passed:      %0d", pass_count);
        $display("Failed:      %0d", test_count - pass_count);
        
        if (pass_count == test_count) begin
            $display("🎉 ALL TESTS PASSED! ALU is working correctly.");
        end else begin
            $display("❌ Some tests failed. Please review the ALU implementation.");
        end
        
        $finish;
    end
    
    // Generate VCD file for waveform analysis
    initial begin
        $dumpfile("alu_test.vcd");
        $dumpvars(0, tb_alu);
    end

endmodule

waveforms/alu_test.vcd
$date
	Wed Sep 24 11:07:04 2025
$end
$version
	Icarus Verilog
$end
$timescale
	1ps
$end
$scope module tb_alu $end
$var wire 1 ! zero $end
$var wire 32 " result [31:0] $end
$var wire 1 # overflow $end
$var wire 1 $ carry $end
$var parameter 4 % ALU_ADD $end
$var parameter 4 & ALU_AND $end
$var parameter 4 ' ALU_OR $end
$var parameter 4 ( ALU_SLL $end
$var parameter 4 ) ALU_SLT $end
$var parameter 4 * ALU_SLTU $end
$var parameter 4 + ALU_SRA $end
$var parameter 4 , ALU_SRL $end
$var parameter 4 - ALU_SUB $end
$var parameter 4 . ALU_XOR $end
$var reg 32 / a [31:0] $end
$var reg 4 0 alu_op [3:0] $end
$var reg 32 1 b [31:0] $end
$var integer 32 2 pass_count [31:0] $end
$var integer 32 3 test_count [31:0] $end
$scope module dut $end
$var wire 32 4 a [31:0] $end
$var wire 4 5 alu_op [3:0] $end
$var wire 32 6 b [31:0] $end
$var wire 1 ! zero $end
$var wire 33 7 sub_result [32:0] $end
$var wire 1 8 result_sign $end
$var wire 1 # overflow $end
$var wire 1 $ carry $end
$var wire 1 9 b_sign $end
$var wire 33 : add_result [32:0] $end
$var wire 1 ; a_sign $end
$var parameter 4 < ALU_ADD $end
$var parameter 4 = ALU_AND $end
$var parameter 4 > ALU_OR $end
$var parameter 4 ? ALU_SLL $end
$var parameter 4 @ ALU_SLT $end
$var parameter 4 A ALU_SLTU $end
$var parameter 4 B ALU_SRA $end
$var parameter 4 C ALU_SRL $end
$var parameter 4 D ALU_SUB $end
$var parameter 4 E ALU_XOR $end
$var reg 32 F result [31:0] $end
$upscope $end
$scope task check_result $end
$var reg 1 G expected_carry $end
$var reg 1 H expected_overflow $end
$var reg 32 I expected_result [31:0] $end
$var reg 1 J expected_zero $end
$var reg 160 K test_name [160:1] $end
$upscope $end
$upscope $end
$enddefinitions $end
$comment Show the parameter values. $end
$dumpall
b100 E
b1 D
b1000 C
b1001 B
b110 A
b101 @
b111 ?
b11 >
b10 =
b0 <
b100 .
b1 -
b1000 ,
b1001 +
b110 *
b101 )
b111 (
b11 '
b10 &
b0 %
$end
#0
$dumpvars
b100000101000100010001000011101000100000001101010010000000101011001000000011001100100000001111010010000000111000 K
0J
b1000 I
0H
0G
b1000 F
0;
b1000 :
09
08
b10 7
b11 6
b0 5
b101 4
b1 3
b0 2
b11 1
b0 0
b101 /
0$
0#
b1000 "
0!
$end
#1000
1$
1!
b0 "
b0 F
1;
b10 3
b11101000100000001011010011000100100000001010110010000000110001001000000011110100100000001100000010000000101000011000110110000101110010011100100111100100101001 K
1G
1J
b0 I
b1 1
b1 6
b100000000000000000000000000000000 :
b11111111111111111111111111111110 7
b11111111111111111111111111111111 /
b11111111111111111111111111111111 4
b1 2
#2000
1#
18
0$
0!
b10000000000000000000000000000000 "
b10000000000000000000000000000000 F
0;
b11 3
b10000010100010001000100001110100010000001101111011101100110010101110010011001100110110001101111011101110010000001110100011001010111001101110100 K
0G
1H
0J
b10000000000000000000000000000000 I
b10000000000000000000000000000000 :
b1111111111111111111111111111110 7
b1111111111111111111111111111111 /
b1111111111111111111111111111111 4
b10 2
#3000
08
0#
b101 "
b101 F
b100 3
b101001101010101010000100011101000100000001110000010000000101101001000000011001100100000001111010010000000110101 K
0H
b101 I
b1 0
b1 5
b11 1
b11 6
b1011 :
b101 7
b1000 /
b1000 4
b11 2
#4000
1$
18
b11111111111111111111111111111011 "
b11111111111111111111111111111011 F
b101 3
b10000000110011001000000010110100100000001110000010000000111101001000000010110100110101001000000010100001100010011011110111001001110010011011110111011100101001 K
1G
b11111111111111111111111111111011 I
b1000 1
b1000 6
b1011 :
b111111111111111111111111111111011 7
b11 /
b11 4
b100 2
#5000
1#
0$
08
b1111111111111111111111111111111 "
b1111111111111111111111111111111 F
1;
b110 3
b10100110101010101000010001110100010000001101111011101100110010101110010011001100110110001101111011101110010000001110100011001010111001101110100 K
0G
1H
b1111111111111111111111111111111 I
b1 1
b1 6
b10000000000000000000000000000001 :
b1111111111111111111111111111111 7
b10000000000000000000000000000000 /
b10000000000000000000000000000000 4
b101 2
#6000
0#
1!
b0 "
b0 F
b111 3
b10000001000110001100000100011000110000010001100011000001000110001100000010000000100110001000000011000001000110001100000100011000110000010001100011000001000110 K
0H
1J
b0 I
b10 0
b10 5
b1111000011110000111100001111 1
b1111000011110000111100001111 6
b11111111111111111111111111111111 :
b11100001111000011110000111100001 7
b11110000111100001111000011110000 /
b11110000111100001111000011110000 4
b110 2
#7000
0!
b10010001101000101011001111000 "
b10010001101000101011001111000 F
b1000 3
b10000001000110010001100100011001000110010001100100011001000110010001100010000000100110001000000011000100110010001100110011010000110101001101100011011100111000 K
0J
b10010001101000101011001111000 I
b10010001101000101011001111000 1
b10010001101000101011001111000 6
b100010010001101000101011001110111 :
b11101101110010111010100110000111 7
b11111111111111111111111111111111 /
b11111111111111111111111111111111 4
b111 2
#8000
18
b11111111111111111111111111111111 "
b11111111111111111111111111111111 F
b1001 3
b10000001000110001100000100011000110000010001100011000001000110001100000010000001111100001000000011000001000110001100000100011000110000010001100011000001000110 K
b11111111111111111111111111111111 I
b11 0
b11 5
b1111000011110000111100001111 1
b1111000011110000111100001111 6
b11111111111111111111111111111111 :
b11100001111000011110000111100001 7
b11110000111100001111000011110000 /
b11110000111100001111000011110000 4
b1000 2
#9000
08
1!
b0 "
b0 F
0;
b1010 3
b1001111010100100011101000100000001100000010000001111100001000000011000000100000001111010010000000110000 K
1J
b0 I
b0 1
b0 6
b0 :
b0 7
b0 /
b0 4
b1001 2
#10000
18
0!
b11111111111111111111111111111111 "
b11111111111111111111111111111111 F
1;
b1011 3
b10000001000110001100000100011000110000010001100011000001000110001100000010000001011110001000000011000001000110001100000100011000110000010001100011000001000110 K
0J
b11111111111111111111111111111111 I
b100 0
b100 5
b1111000011110000111100001111 1
b1111000011110000111100001111 6
b11111111111111111111111111111111 :
b11100001111000011110000111100001 7
b11110000111100001111000011110000 /
b11110000111100001111000011110000 4
b1010 2
#11000
08
1!
b0 "
b0 F
0;
b1100 3
b101100001001111010100100011101000100000011100110110000101101101011001010010000001110110011000010110110001110101011001010111001100100000001111010010000000110000 K
1J
b0 I
b10010001101000101011001111000 1
b10010001101000101011001111000 6
b100100011010001010110011110000 :
b0 7
b10010001101000101011001111000 /
b10010001101000101011001111000 4
b1011 2
#12000
0!
b1 "
b1 F
b1101 3
b101001101001100010101000011101000100000001101010010000000111100001000000011100000100000001111010010000001110100011100100111010101100101 K
0J
b1 I
b101 0
b101 5
b1000 1
b1000 6
b1101 :
b111111111111111111111111111111101 7
b101 /
b101 4
b1100 2
#13000
1!
b0 "
b0 F
b1110 3
b10100110100110001010100001110100010000000111000001000000011110000100000001101010010000000111101001000000110011001100001011011000111001101100101 K
1J
b0 I
b101 1
b101 6
b1101 :
b11 7
b1000 /
b1000 4
b1101 2
#14000
0!
b1 "
b1 F
1;
b1111 3
b10100110100110001010100001110100010000000101101001100010010000000111100001000000011000100100000001111010010000001110100011100100111010101100101 K
0J
b1 I
b1 1
b1 6
b100000000000000000000000000000000 :
b11111111111111111111111111111110 7
b11111111111111111111111111111111 /
b11111111111111111111111111111111 4
b1110 2
#15000
1!
b0 "
b0 F
b10000 3
b100011001000110010001100100011001000110010001100100011001000110001000000011110000100000001100010010000000111101001000000110011001100001011011000111001101100101 K
1J
b0 I
b110 0
b110 5
b1111 2
#16000
19
0!
b1 "
b1 F
0;
b10001 3
b10000000111100001000000011000001111000010001100100011001000110010001100100011001000110010001100100011000100000001111010010000001110100011100100111010101100101 K
0J
b1 I
b11111111111111111111111111111111 1
b11111111111111111111111111111111 6
b100000000000000000000000000000000 :
b100000000000000000000000000000010 7
b1 /
b1 4
b10000 2
#17000
b10000 "
b10000 F
09
b10010 3
b1010011010011000100110000111010001000000011000100100000001111000011110000100000001101000010000000111101001000000011000100110110 K
b10000 I
b111 0
b111 5
b101 :
b111111111111111111111111111111101 7
b100 1
b100 6
b10001 2
#18000
b110100010101100111100000000000 "
b110100010101100111100000000000 F
b10011 3
b101001101001100010011000011101000100000001100000111100000110001001100100011001100110100001101010011011000110111001110000010000000111100001111000010000000111000 K
b110100010101100111100000000000 I
b1000 1
b1000 6
b10010001101000101011010000000 :
b10010001101000101011001110000 7
b10010001101000101011001111000 /
b10010001101000101011001111000 4
b10010 2
#19000
b1 "
b1 F
b10100 3
b1010011010100100100110000111010001000000011000100110110001000000011111000111110001000000011010000100000001111010010000000110001 K
b1 I
b1000 0
b1000 5
b100 1
b100 6
b10100 :
b1100 7
b10000 /
b10000 4
b10011 2
#20000
b1000000000000000000000000000000 "
b1000000000000000000000000000000 F
1;
b10101 3
b101001101010010010011000011101000100000001100000111100000111000001100000011000000110000001100000011000000110000001100000010000000111110001111100010000000110001 K
b1000000000000000000000000000000 I
b1 1
b1 6
b10000000000000000000000000000001 :
b1111111111111111111111111111111 7
b10000000000000000000000000000000 /
b10000000000000000000000000000000 4
b10100 2
#21000
18
b11000000000000000000000000000000 "
b11000000000000000000000000000000 F
b10110 3
b10000000111110001111100011111000100000001100010010000000101000011100110110100101100111011011100010000001100101011110000111010001100101011011100110010000101001 K
b11000000000000000000000000000000 I
b1001 0
b1001 5
b10101 2
#22000
08
b100000000000000000000000000000 "
b100000000000000000000000000000 F
0;
b10111 3
b101001001000001001110100010000000110000011110000011010000110000001100000011000000110000001100000011000000110000001000000011111000111110001111100010000000110001 K
b100000000000000000000000000000 I
b1000000000000000000000000000001 :
b111111111111111111111111111111 7
b1000000000000000000000000000000 /
b1000000000000000000000000000000 4
b10110 2
#23000
b10111 2
