phase2_rtl_foundation/memory.v
// Simple Memory Module for RISC-V CPU
// Array-based memory with byte-addressable storage
// Supports word (32-bit) read/write operations

module memory (
    input clk,                    // Clock
    input reset_n,                // Active-low reset
    
    // Memory interface
    input  [31:0] addr,           // Memory address
    input  [31:0] write_data,     // Data to write
    input         mem_read,       // Memory read enable
    input         mem_write,      // Memory write enable
    input  [3:0]  byte_enable,    // Byte enable (for partial writes)
    output reg [31:0] read_data,  // Data read from memory
    output reg    ready           // Memory operation complete
);

    // Memory array - 1KB of memory (256 words)
    // In a real CPU, this would be much larger
    reg [31:0] mem_array [255:0];
    
    // Address calculation (word-aligned)
    wire [7:0] word_addr = addr[9:2];  // Use bits [9:2] for word addressing
    
    // Initialize memory
    integer i;
    always @(posedge clk or negedge reset_n) begin
        if (!reset_n) begin
            // Clear memory on reset
            for (i = 0; i < 256; i = i + 1) begin
                mem_array[i] <= 32'h0;
            end
            read_data <= 32'h0;
            ready <= 1'b0;
        end else begin
            ready <= 1'b0;  // Default not ready
            
            if (mem_read) begin
                // Read operation
                read_data <= mem_array[word_addr];
                ready <= 1'b1;
            end else if (mem_write) begin
                // Write operation with byte enable support
                if (byte_enable[0]) mem_array[word_addr][7:0]   <= write_data[7:0];
                if (byte_enable[1]) mem_array[word_addr][15:8]  <= write_data[15:8];
                if (byte_enable[2]) mem_array[word_addr][23:16] <= write_data[23:16];
                if (byte_enable[3]) mem_array[word_addr][31:24] <= write_data[31:24];
                ready <= 1'b1;
            end
        end
    end

endmodule

testbenches/tb_memory.v
// Testbench for Memory module
// Tests read/write operations, byte enable functionality, and address handling

`timescale 1ns/1ps

module tb_memory;

    // Testbench signals
    reg clk, reset_n;
    reg [31:0] addr, write_data;
    reg mem_read, mem_write;
    reg [3:0] byte_enable;
    wire [31:0] read_data;
    wire ready;
    
    // Test tracking
    integer test_count = 0;
    integer pass_count = 0;
    
    // Instantiate memory module
    memory dut (
        .clk(clk),
        .reset_n(reset_n),
        .addr(addr),
        .write_data(write_data),
        .mem_read(mem_read),
        .mem_write(mem_write),
        .byte_enable(byte_enable),
        .read_data(read_data),
        .ready(ready)
    );
    
    // Clock generation
    initial begin
        clk = 0;
        forever #5 clk = ~clk;  // 10ns period
    end
    
    // Task to check memory read
    task check_read;
        input [31:0] address;
        input [31:0] expected_data;
        input [8*30:1] test_name;
        begin
            test_count = test_count + 1;
            addr = address;
            mem_read = 1'b1;
            mem_write = 1'b0;
            @(posedge clk);
            #1; // Small delay for signals to settle
            
            if (read_data === expected_data && ready === 1'b1) begin
                $display("✅ PASS: %s", test_name);
                $display("   Read addr=%h -> data=%h", address, read_data);
                pass_count = pass_count + 1;
            end else begin
                $display("❌ FAIL: %s", test_name);
                $display("   Address: %h", address);
                $display("   Expected: data=%h, ready=1", expected_data);
                $display("   Got:      data=%h, ready=%b", read_data, ready);
            end
            
            mem_read = 1'b0;
            #1;
            $display("");
        end
    endtask
    
    // Task to write to memory
    task write_memory;
        input [31:0] address;
        input [31:0] data;
        input [3:0] be;
        begin
            addr = address;
            write_data = data;
            byte_enable = be;
            mem_read = 1'b0;
            mem_write = 1'b1;
            @(posedge clk);
            #1; // Allow write to complete
            mem_write = 1'b0;
            #1;
        end
    endtask
    
    // Main test sequence
    initial begin
        $display("=== Memory Testbench Starting ===");
        $display("");
        
        // Initialize signals
        reset_n = 1'b0;
        addr = 32'h0;
        write_data = 32'h0;
        mem_read = 1'b0;
        mem_write = 1'b0;
        byte_enable = 4'b0000;
        
        // Reset sequence
        #50;
        reset_n = 1'b1;
        #20;
        
        // Test 1: Check that memory is zero after reset
        $display("--- Testing Reset Behavior ---");
        check_read(32'h00000000, 32'h00000000, "Reset: addr 0x00 should be zero");
        check_read(32'h00000100, 32'h00000000, "Reset: addr 0x100 should be zero");
        
        // Test 2: Basic word write/read
        $display("--- Testing Word Write/Read ---");
        write_memory(32'h00000000, 32'h12345678, 4'b1111);
        check_read(32'h00000000, 32'h12345678, "Word write/read at addr 0x00");
        
        write_memory(32'h00000004, 32'hDEADBEEF, 4'b1111);
        check_read(32'h00000004, 32'hDEADBEEF, "Word write/read at addr 0x04");
        
        // Test 3: Byte enable functionality
        $display("--- Testing Byte Enable ---");
        write_memory(32'h00000008, 32'h00000000, 4'b1111); // Clear first
        write_memory(32'h00000008, 32'hAABBCCDD, 4'b0001); // Write only byte 0
        check_read(32'h00000008, 32'h000000DD, "Byte enable [0] only");
        
        write_memory(32'h00000008, 32'hAABBCCDD, 4'b0010); // Write only byte 1
        check_read(32'h00000008, 32'h0000CCDD, "Byte enable [1] added");
        
        write_memory(32'h00000008, 32'hAABBCCDD, 4'b1100); // Write bytes 2,3
        check_read(32'h00000008, 32'hAABBCCDD, "Byte enable [3:2] added");
        
        // Test 4: Different addresses
        $display("--- Testing Address Decoding ---");
        write_memory(32'h00000010, 32'h11111111, 4'b1111);
        write_memory(32'h00000020, 32'h22222222, 4'b1111);
        write_memory(32'h00000030, 32'h33333333, 4'b1111);
        
        check_read(32'h00000010, 32'h11111111, "Address 0x10");
        check_read(32'h00000020, 32'h22222222, "Address 0x20");
        check_read(32'h00000030, 32'h33333333, "Address 0x30");
        
        // Test 5: Word alignment (addresses should be word-aligned)
        $display("--- Testing Word Alignment ---");
        write_memory(32'h00000040, 32'hABCDEF00, 4'b1111);
        check_read(32'h00000040, 32'hABCDEF00, "Aligned addr 0x40");
        check_read(32'h00000041, 32'hABCDEF00, "Unaligned 0x41 -> same word");
        check_read(32'h00000042, 32'hABCDEF00, "Unaligned 0x42 -> same word");
        check_read(32'h00000043, 32'hABCDEF00, "Unaligned 0x43 -> same word");
        
        // Test 6: Memory boundaries
        $display("--- Testing Memory Boundaries ---");
        write_memory(32'h000003FC, 32'hFFFFFFFF, 4'b1111); // Last word
        check_read(32'h000003FC, 32'hFFFFFFFF, "Last memory location");
        
        // Test 7: Overwrite existing data
        $display("--- Testing Data Overwrite ---");
        write_memory(32'h00000000, 32'h4E455756, 4'b1111);
        check_read(32'h00000000, 32'h4E455756, "Overwrite previous data");
        
        // Test 8: Partial byte writes
        $display("--- Testing Partial Byte Writes ---");
        write_memory(32'h00000050, 32'h00000000, 4'b1111); // Clear
        write_memory(32'h00000050, 32'hFF000000, 4'b1000); // Write byte 3 only
        check_read(32'h00000050, 32'hFF000000, "Byte 3 write only");
        
        write_memory(32'h00000050, 32'h00FF0000, 4'b0100); // Write byte 2 only
        check_read(32'h00000050, 32'hFFFF0000, "Byte 2 added");
        
        // Test Summary
        $display("=== Memory Test Summary ===");
        $display("Total tests: %0d", test_count);
        $display("Passed:      %0d", pass_count);
        $display("Failed:      %0d", test_count - pass_count);
        
        if (pass_count == test_count) begin
            $display("🎉 ALL TESTS PASSED! Memory module is working correctly.");
        end else begin
            $display("❌ Some tests failed. Please review the Memory implementation.");
        end
        
        $finish;
    end
    
    // Generate VCD file for waveform analysis
    initial begin
        $dumpfile("memory_test.vcd");
        $dumpvars(0, tb_memory);
    end

endmodule

waveforms/memory_test.vcd
$date
	Wed Sep 24 11:07:04 2025
$end
$version
	Icarus Verilog
$end
$timescale
	1ps
$end
$scope module tb_memory $end
$var wire 1 ! ready $end
$var wire 32 " read_data [31:0] $end
$var reg 32 # addr [31:0] $end
$var reg 4 $ byte_enable [3:0] $end
$var reg 1 % clk $end
$var reg 1 & mem_read $end
$var reg 1 ' mem_write $end
$var reg 1 ( reset_n $end
$var reg 32 ) write_data [31:0] $end
$var integer 32 * pass_count [31:0] $end
$var integer 32 + test_count [31:0] $end
$scope module dut $end
$var wire 32 , addr [31:0] $end
$var wire 4 - byte_enable [3:0] $end
$var wire 1 % clk $end
$var wire 1 & mem_read $end
$var wire 1 ' mem_write $end
$var wire 1 ( reset_n $end
$var wire 32 . write_data [31:0] $end
$var wire 8 / word_addr [7:0] $end
$var reg 32 0 read_data [31:0] $end
$var reg 1 ! ready $end
$var integer 32 1 i [31:0] $end
$upscope $end
$scope task check_read $end
$var reg 32 2 address [31:0] $end
$var reg 32 3 expected_data [31:0] $end
$var reg 240 4 test_name [240:1] $end
$upscope $end
$scope task write_memory $end
$var reg 32 5 address [31:0] $end
$var reg 4 6 be [3:0] $end
$var reg 32 7 data [31:0] $end
$upscope $end
$upscope $end
$enddefinitions $end
$comment Show the parameter values. $end
$dumpall
$end
#0
$dumpvars
bx 7
bx 6
bx 5
bx 4
bx 3
bx 2
b100000000 1
b0 0
b0 /
b0 .
b0 -
b0 ,
b0 +
b0 *
b0 )
0(
0'
0&
0%
b0 $
b0 #
b0 "
0!
$end
#5000
b100000000 1
1%
#10000
0%
#15000
b100000000 1
1%
#20000
0%
#25000
b100000000 1
1%
#30000
0%
#35000
b100000000 1
1%
#40000
0%
#45000
b100000000 1
1%
#50000
0%
1(
#55000
1%
#60000
0%
#65000
1%
#70000
0%
1&
b1 +
b11001010111001101100101011101000011101000100000011000010110010001100100011100100010000000110000011110000011000000110000001000000111001101101000011011110111010101101100011001000010000001100010011001010010000001111010011001010111001001101111 4
b0 3
b0 2
#75000
1!
1%
#76000
0&
b1 *
#77000
b1000000 /
1&
b100000000 #
b100000000 ,
b10 +
b11100110110010101110100001110100010000001100001011001000110010001110010001000000011000001111000001100010011000000110000001000000111001101101000011011110111010101101100011001000010000001100010011001010010000001111010011001010111001001101111 4
b100000000 2
#80000
0%
#85000
1!
1%
#86000
0&
b10 *
#87000
b0 /
1'
b1111 $
b1111 -
b10010001101000101011001111000 )
b10010001101000101011001111000 .
b0 #
b0 ,
b1111 6
b10010001101000101011001111000 7
b0 5
#90000
0%
#95000
1!
1%
#96000
0'
#97000
1&
b11 +
b1010111011011110111001001100100001000000111011101110010011010010111010001100101001011110111001001100101011000010110010000100000011000010111010000100000011000010110010001100100011100100010000000110000011110000011000000110000 4
b10010001101000101011001111000 3
b0 2
#100000
0%
#105000
b10010001101000101011001111000 "
b10010001101000101011001111000 0
1!
1%
#106000
0&
b11 *
#107000
b1 /
1'
b11011110101011011011111011101111 )
b11011110101011011011111011101111 .
b100 #
b100 ,
b11011110101011011011111011101111 7
b100 5
#110000
0%
#115000
1!
1%
#116000
0'
#117000
1&
b100 +
b1010111011011110111001001100100001000000111011101110010011010010111010001100101001011110111001001100101011000010110010000100000011000010111010000100000011000010110010001100100011100100010000000110000011110000011000000110100 4
b11011110101011011011111011101111 3
b100 2
#120000
0%
#125000
b11011110101011011011111011101111 "
b11011110101011011011111011101111 0
1!
1%
#126000
0&
b100 *
#127000
b10 /
1'
b0 )
b0 .
b1000 #
b1000 ,
b0 7
b1000 5
#130000
0%
#135000
1!
1%
#136000
0'
#137000
1'
b1 $
b1 -
b10101010101110111100110011011101 )
b10101010101110111100110011011101 .
b1 6
b10101010101110111100110011011101 7
#140000
0%
#145000
1!
1%
#146000
0'
#147000
1&
b101 +
b100001001111001011101000110010100100000011001010110111001100001011000100110110001100101001000000101101100110000010111010010000001101111011011100110110001111001 4
b11011101 3
b1000 2
#150000
0%
#155000
b11011101 "
b11011101 0
1!
1%
#156000
0&
b101 *
#157000
1'
b10 $
b10 -
b10 6
#160000
0%
#165000
1!
1%
#166000
0'
#167000
1&
b110 +
b10000100111100101110100011001010010000001100101011011100110000101100010011011000110010100100000010110110011000101011101001000000110000101100100011001000110010101100100 4
b1100110011011101 3
#170000
0%
#175000
b1100110011011101 "
b1100110011011101 0
1!
1%
#176000
0&
b110 *
#177000
1'
b1100 $
b1100 -
b1100 6
#180000
0%
#185000
1!
1%
#186000
0'
#187000
1&
b111 +
b100001001111001011101000110010100100000011001010110111001100001011000100110110001100101001000000101101100110011001110100011001001011101001000000110000101100100011001000110010101100100 4
b10101010101110111100110011011101 3
#190000
0%
#195000
b10101010101110111100110011011101 "
b10101010101110111100110011011101 0
1!
1%
#196000
0&
b111 *
#197000
b100 /
1'
b1111 $
b1111 -
b10001000100010001000100010001 )
b10001000100010001000100010001 .
b10000 #
b10000 ,
b1111 6
b10001000100010001000100010001 7
b10000 5
#200000
0%
#205000
1!
1%
#206000
0'
#207000
b1000 /
1'
b100010001000100010001000100010 )
b100010001000100010001000100010 .
b100000 #
b100000 ,
b100010001000100010001000100010 7
b100000 5
#210000
0%
#215000
1!
1%
#216000
0'
#217000
b1100 /
1'
b110011001100110011001100110011 )
b110011001100110011001100110011 .
b110000 #
b110000 ,
b110011001100110011001100110011 7
b110000 5
#220000
0%
#225000
1!
1%
#226000
0'
#227000
b100 /
1&
b10000 #
b10000 ,
b1000 +
b10000010110010001100100011100100110010101110011011100110010000000110000011110000011000100110000 4
b10001000100010001000100010001 3
b10000 2
#230000
0%
#235000
b10001000100010001000100010001 "
b10001000100010001000100010001 0
1!
1%
#236000
0&
b1000 *
#237000
b1000 /
1&
b100000 #
b100000 ,
b1001 +
b10000010110010001100100011100100110010101110011011100110010000000110000011110000011001000110000 4
b100010001000100010001000100010 3
b100000 2
#240000
0%
#245000
b100010001000100010001000100010 "
b100010001000100010001000100010 0
1!
1%
#246000
0&
b1001 *
#247000
b1100 /
1&
b110000 #
b110000 ,
b1010 +
b10000010110010001100100011100100110010101110011011100110010000000110000011110000011001100110000 4
b110011001100110011001100110011 3
b110000 2
#250000
0%
#255000
b110011001100110011001100110011 "
b110011001100110011001100110011 0
1!
1%
#256000
0&
b1010 *
#257000
b10000 /
1'
b10101011110011011110111100000000 )
b10101011110011011110111100000000 .
b1000000 #
b1000000 ,
b10101011110011011110111100000000 7
b1000000 5
#260000
0%
#265000
1!
1%
#266000
0'
#267000
1&
b1011 +
b100000101101100011010010110011101101110011001010110010000100000011000010110010001100100011100100010000000110000011110000011010000110000 4
b10101011110011011110111100000000 3
b1000000 2
#270000
0%
#275000
b10101011110011011110111100000000 "
b10101011110011011110111100000000 0
1!
1%
#276000
0&
b1011 *
#277000
1&
b1000001 #
b1000001 ,
b1100 +
b10101010110111001100001011011000110100101100111011011100110010101100100001000000011000001111000001101000011000100100000001011010011111000100000011100110110000101101101011001010010000001110111011011110111001001100100 4
b1000001 2
#280000
0%
#285000
1!
1%
#286000
0&
b1100 *
#287000
1&
b1000010 #
b1000010 ,
b1101 +
b10101010110111001100001011011000110100101100111011011100110010101100100001000000011000001111000001101000011001000100000001011010011111000100000011100110110000101101101011001010010000001110111011011110111001001100100 4
b1000010 2
#290000
0%
#295000
1!
1%
#296000
0&
b1101 *
#297000
1&
b1000011 #
b1000011 ,
b1110 +
b10101010110111001100001011011000110100101100111011011100110010101100100001000000011000001111000001101000011001100100000001011010011111000100000011100110110000101101101011001010010000001110111011011110111001001100100 4
b1000011 2
#300000
0%
#305000
1!
1%
#306000
0&
b1110 *
#307000
b11111111 /
1'
b11111111111111111111111111111111 )
b11111111111111111111111111111111 .
b1111111100 #
b1111111100 ,
b11111111111111111111111111111111 7
b1111111100 5
#310000
0%
#315000
1!
1%
#316000
0'
#317000
1&
b1111 +
b100110001100001011100110111010000100000011011010110010101101101011011110111001001111001001000000110110001101111011000110110000101110100011010010110111101101110 4
b11111111111111111111111111111111 3
b1111111100 2
#320000
0%
#325000
b11111111111111111111111111111111 "
b11111111111111111111111111111111 0
1!
1%
#326000
0&
b1111 *
#327000
b0 /
1'
b1001110010001010101011101010110 )
b1001110010001010101011101010110 .
b0 #
b0 ,
b1001110010001010101011101010110 7
b0 5
#330000
0%
#335000
1!
1%
#336000
0'
#337000
1&
b10000 +
b100111101110110011001010111001001110111011100100110100101110100011001010010000001110000011100100110010101110110011010010110111101110101011100110010000001100100011000010111010001100001 4
b1001110010001010101011101010110 3
b0 2
#340000
0%
#345000
b1001110010001010101011101010110 "
b1001110010001010101011101010110 0
1!
1%
#346000
0&
b10000 *
#347000
b10100 /
1'
b0 )
b0 .
b1010000 #
b1010000 ,
b0 7
b1010000 5
#350000
0%
#355000
1!
1%
#356000
0'
#357000
1'
b1000 $
b1000 -
b11111111000000000000000000000000 )
b11111111000000000000000000000000 .
b1000 6
b11111111000000000000000000000000 7
#360000
0%
#365000
1!
1%
#366000
0'
#367000
1&
b10001 +
b100001001111001011101000110010100100000001100110010000001110111011100100110100101110100011001010010000001101111011011100110110001111001 4
b11111111000000000000000000000000 3
b1010000 2
#370000
0%
#375000
b11111111000000000000000000000000 "
b11111111000000000000000000000000 0
1!
1%
#376000
0&
b10001 *
#377000
1'
b100 $
b100 -
b111111110000000000000000 )
b111111110000000000000000 .
b100 6
b111111110000000000000000 7
#380000
0%
#385000
1!
1%
#386000
0'
#387000
1&
b10010 +
b10000100111100101110100011001010010000000110010001000000110000101100100011001000110010101100100 4
b11111111111111110000000000000000 3
#390000
0%
#395000
b11111111111111110000000000000000 "
b11111111111111110000000000000000 0
1!
1%
#396000
0&
b10010 *
