phase2_rtl_foundation/register_file.v
// Register File for RISC-V CPU
// 32 general-purpose registers (x0-x31)
// x0 is hardwired to zero
// Dual read ports, single write port

module register_file (
    input clk,                    // Clock
    input reset_n,                // Active-low reset
    
    // Read ports
    input  [4:0]  rs1_addr,       // Read address 1 (source register 1)
    input  [4:0]  rs2_addr,       // Read address 2 (source register 2)
    output [31:0] rs1_data,       // Read data 1
    output [31:0] rs2_data,       // Read data 2
    
    // Write port
    input  [4:0]  rd_addr,        // Write address (destination register)
    input  [31:0] rd_data,        // Write data
    input         wr_enable       // Write enable
);

    // Register array - 32 registers of 32 bits each
    reg [31:0] registers [31:0];
    
    // Initialize registers
    integer i;
    always @(posedge clk or negedge reset_n) begin
        if (!reset_n) begin
            // Reset all registers to zero
            for (i = 0; i < 32; i = i + 1) begin
                registers[i] <= 32'h0;
            end
        end else if (wr_enable && rd_addr != 5'h0) begin
            // Write to register (except x0 which is always zero)
            registers[rd_addr] <= rd_data;
        end
    end
    
    // Read operations (combinational)
    // x0 is always zero, other registers read from array
    assign rs1_data = (rs1_addr == 5'h0) ? 32'h0 : registers[rs1_addr];
    assign rs2_data = (rs2_addr == 5'h0) ? 32'h0 : registers[rs2_addr];

endmodule

testbenches/tb_register_file.v
// Testbench for Register File module
// Tests dual read ports, write functionality, and x0 hardwired zero

`timescale 1ns/1ps

module tb_register_file;

    // Testbench signals
    reg clk, reset_n;
    reg [4:0] rs1_addr, rs2_addr, rd_addr;
    reg [31:0] rd_data;
    reg wr_enable;
    wire [31:0] rs1_data, rs2_data;
    
    // Test tracking
    integer test_count = 0;
    integer pass_count = 0;
    integer j, k, errors;
    
    // Instantiate register file
    register_file dut (
        .clk(clk),
        .reset_n(reset_n),
        .rs1_addr(rs1_addr),
        .rs2_addr(rs2_addr),
        .rs1_data(rs1_data),
        .rs2_data(rs2_data),
        .rd_addr(rd_addr),
        .rd_data(rd_data),
        .wr_enable(wr_enable)
    );
    
    // Clock generation
    initial begin
        clk = 0;
        forever #5 clk = ~clk;  // 10ns period
    end
    
    // Task to check register read
    task check_read;
        input [4:0] addr1, addr2;
        input [31:0] expected1, expected2;
        input [8*30:1] test_name;
        begin
            test_count = test_count + 1;
            rs1_addr = addr1;
            rs2_addr = addr2;
            #1; // Small delay for combinational logic
            
            if (rs1_data === expected1 && rs2_data === expected2) begin
                $display("✅ PASS: %s", test_name);
                $display("   Read x%0d=%h, x%0d=%h", addr1, rs1_data, addr2, rs2_data);
                pass_count = pass_count + 1;
            end else begin
                $display("❌ FAIL: %s", test_name);
                $display("   Expected: x%0d=%h, x%0d=%h", addr1, expected1, addr2, expected2);
                $display("   Got:      x%0d=%h, x%0d=%h", addr1, rs1_data, addr2, rs2_data);
            end
            $display("");
        end
    endtask
    
    // Task to write to register
    task write_register;
        input [4:0] addr;
        input [31:0] data;
        begin
            rd_addr = addr;
            rd_data = data;
            wr_enable = 1'b1;
            #10; // Wait for clock edge
            wr_enable = 1'b0;
            #10; // Allow write to complete
        end
    endtask
    
    // Main test sequence
    initial begin
        $display("=== Register File Testbench Starting ===");
        $display("");
        
        // Initialize signals
        reset_n = 1'b0;
        rs1_addr = 5'h0;
        rs2_addr = 5'h0;
        rd_addr = 5'h0;
        rd_data = 32'h0;
        wr_enable = 1'b0;
        
        // Reset sequence
        #50;
        reset_n = 1'b1;
        #20;
        
        // Test 1: Check that all registers are zero after reset
        $display("--- Testing Reset Behavior ---");
        check_read(5'h0, 5'h1, 32'h0, 32'h0, "Reset: x0 and x1 should be zero");
        check_read(5'h1F, 5'h1E, 32'h0, 32'h0, "Reset: x31 and x30 should be zero");
        
        // Test 2: Write to various registers and read back
        $display("--- Testing Write/Read Operations ---");
        write_register(5'h1, 32'h12345678);
        check_read(5'h1, 5'h0, 32'h12345678, 32'h0, "Write x1=0x12345678");
        
        write_register(5'h2, 32'hDEADBEEF);
        check_read(5'h2, 5'h1, 32'hDEADBEEF, 32'h12345678, "Write x2=0xDEADBEEF");
        
        write_register(5'h1F, 32'hCAFEBABE);
        check_read(5'h1F, 5'h2, 32'hCAFEBABE, 32'hDEADBEEF, "Write x31=0xCAFEBABE");
        
        // Test 3: Verify x0 is always zero (hardwired)
        $display("--- Testing x0 Hardwired Zero ---");
        write_register(5'h0, 32'hFFFFFFFF);
        check_read(5'h0, 5'h1, 32'h0, 32'h12345678, "x0 should remain zero after write");
        
        // Test 4: Test dual read ports with same address
        $display("--- Testing Dual Read Ports ---");
        check_read(5'h1, 5'h1, 32'h12345678, 32'h12345678, "Dual read same register");
        
        // Test 5: Write and read in same cycle
        $display("--- Testing Write/Read Timing ---");
        write_register(5'h3, 32'h87654321);
        check_read(5'h3, 5'h2, 32'h87654321, 32'hDEADBEEF, "Immediate read after write");
        
        // Test 6: Write enable functionality
        $display("--- Testing Write Enable ---");
        rd_addr = 5'h4;
        rd_data = 32'hABCDEF00;
        wr_enable = 1'b0;  // Write disabled
        @(posedge clk);
        check_read(5'h4, 5'h0, 32'h0, 32'h0, "Write disabled - x4 should remain zero");
        
        // Test 7: Overwrite existing register
        $display("--- Testing Register Overwrite ---");
        write_register(5'h1, 32'h11111111);
        check_read(5'h1, 5'h2, 32'h11111111, 32'hDEADBEEF, "Overwrite x1 with new value");
        
        // Test 8: Test all register addresses
        $display("--- Testing All Register Addresses ---");
        // Write unique pattern to each register
        for (j = 1; j < 32; j = j + 1) begin
            write_register(j[4:0], 32'h1000_0000 | j);
        end
        
        // Read back and verify
        errors = 0;
        for (k = 1; k < 32; k = k + 1) begin
            rs1_addr = k[4:0];
            rs2_addr = 5'h0;
            #1;
            if (rs1_data !== (32'h1000_0000 | k)) begin
                errors = errors + 1;
                $display("❌ Register x%0d: expected %h, got %h", k, 32'h1000_0000 | k, rs1_data);
            end
        end
        
        test_count = test_count + 1;
        if (errors == 0) begin
            $display("✅ PASS: All 31 registers store/retrieve correctly");
            pass_count = pass_count + 1;
        end else begin
            $display("❌ FAIL: %0d registers had errors", errors);
        end
        $display("");
        
        // Test Summary
        $display("=== Register File Test Summary ===");
        $display("Total tests: %0d", test_count);
        $display("Passed:      %0d", pass_count);
        $display("Failed:      %0d", test_count - pass_count);
        
        if (pass_count == test_count) begin
            $display("🎉 ALL TESTS PASSED! Register File is working correctly.");
        end else begin
            $display("❌ Some tests failed. Please review the Register File implementation.");
        end
        
        $finish;
    end
    
    // Generate VCD file for waveform analysis
    initial begin
        $dumpfile("register_file_test.vcd");
        $dumpvars(0, tb_register_file);
    end

endmodule

waveforms/register_file_test.vcd
$date
	Wed Sep 24 11:07:04 2025
$end
$version
	Icarus Verilog
$end
$timescale
	1ps
$end
$scope module tb_register_file $end
$var wire 32 ! rs2_data [31:0] $end
$var wire 32 " rs1_data [31:0] $end
$var reg 1 # clk $end
$var reg 5 $ rd_addr [4:0] $end
$var reg 32 % rd_data [31:0] $end
$var reg 1 & reset_n $end
$var reg 5 ' rs1_addr [4:0] $end
$var reg 5 ( rs2_addr [4:0] $end
$var reg 1 ) wr_enable $end
$var integer 32 * errors [31:0] $end
$var integer 32 + j [31:0] $end
$var integer 32 , k [31:0] $end
$var integer 32 - pass_count [31:0] $end
$var integer 32 . test_count [31:0] $end
$scope module dut $end
$var wire 1 # clk $end
$var wire 5 / rd_addr [4:0] $end
$var wire 32 0 rd_data [31:0] $end
$var wire 1 & reset_n $end
$var wire 5 1 rs1_addr [4:0] $end
$var wire 5 2 rs2_addr [4:0] $end
$var wire 1 ) wr_enable $end
$var wire 32 3 rs2_data [31:0] $end
$var wire 32 4 rs1_data [31:0] $end
$var integer 32 5 i [31:0] $end
$upscope $end
$scope task check_read $end
$var reg 5 6 addr1 [4:0] $end
$var reg 5 7 addr2 [4:0] $end
$var reg 32 8 expected1 [31:0] $end
$var reg 32 9 expected2 [31:0] $end
$var reg 240 : test_name [240:1] $end
$upscope $end
$scope task write_register $end
$var reg 5 ; addr [4:0] $end
$var reg 32 < data [31:0] $end
$upscope $end
$upscope $end
$enddefinitions $end
$comment Show the parameter values. $end
$dumpall
$end
#0
$dumpvars
bx <
bx ;
bx :
bx 9
bx 8
bx 7
bx 6
b100000 5
b0 4
b0 3
b0 2
b0 1
b0 0
b0 /
b0 .
b0 -
bx ,
bx +
bx *
0)
b0 (
b0 '
0&
b0 %
b0 $
0#
b0 "
b0 !
$end
#5000
b100000 5
1#
#10000
0#
#15000
b100000 5
1#
#20000
0#
#25000
b100000 5
1#
#30000
0#
#35000
b100000 5
1#
#40000
0#
#45000
b100000 5
1#
#50000
0#
1&
#55000
1#
#60000
0#
#65000
1#
#70000
0#
b1 (
b1 2
b1 .
b11001010111001101100101011101000011101000100000011110000011000000100000011000010110111001100100001000000111100000110001001000000111001101101000011011110111010101101100011001000010000001100010011001010010000001111010011001010111001001101111 :
b0 9
b0 8
b1 7
b0 6
#71000
b11110 (
b11110 2
b11111 '
b11111 1
b10 .
b11001010111010000111010001000000111100000110011001100010010000001100001011011100110010000100000011110000011001100110000001000000111001101101000011011110111010101101100011001000010000001100010011001010010000001111010011001010111001001101111 :
b11110 7
b11111 6
b1 -
#72000
1)
b10010001101000101011001111000 %
b10010001101000101011001111000 0
b1 $
b1 /
b10010001101000101011001111000 <
b1 ;
b10 -
#75000
1#
#80000
0#
#82000
0)
#85000
1#
#90000
0#
#92000
b10010001101000101011001111000 "
b10010001101000101011001111000 4
b0 (
b0 2
b1 '
b1 1
b11 .
b1010111011100100110100101110100011001010010000001111000001100010011110100110000011110000011000100110010001100110011010000110101001101100011011100111000 :
b10010001101000101011001111000 8
b0 7
b1 6
#93000
1)
b11011110101011011011111011101111 %
b11011110101011011011111011101111 0
b10 $
b10 /
b11011110101011011011111011101111 <
b10 ;
b11 -
#95000
1#
#100000
0#
#103000
0)
#105000
1#
#110000
0#
#113000
b10010001101000101011001111000 !
b10010001101000101011001111000 3
b11011110101011011011111011101111 "
b11011110101011011011111011101111 4
b1 (
b1 2
b10 '
b10 1
b100 .
b1010111011100100110100101110100011001010010000001111000001100100011110100110000011110000100010001000101010000010100010001000010010001010100010101000110 :
b10010001101000101011001111000 9
b11011110101011011011111011101111 8
b1 7
b10 6
#114000
1)
b11001010111111101011101010111110 %
b11001010111111101011101010111110 0
b11111 $
b11111 /
b11001010111111101011101010111110 <
b11111 ;
b100 -
#115000
1#
#120000
0#
#124000
0)
#125000
1#
#130000
0#
#134000
b11011110101011011011111011101111 !
b11011110101011011011111011101111 3
b11001010111111101011101010111110 "
b11001010111111101011101010111110 4
b10 (
b10 2
b11111 '
b11111 1
b101 .
b101011101110010011010010111010001100101001000000111100000110011001100010011110100110000011110000100001101000001010001100100010101000010010000010100001001000101 :
b11011110101011011011111011101111 9
b11001010111111101011101010111110 8
b10 7
b11111 6
#135000
1)
b11111111111111111111111111111111 %
b11111111111111111111111111111111 0
b0 $
b0 /
b11111111111111111111111111111111 <
b0 ;
b101 -
1#
#140000
0#
#145000
1#
0)
#150000
0#
#155000
b10010001101000101011001111000 !
b10010001101000101011001111000 3
b0 "
b0 4
1#
b1 (
b1 2
b0 '
b0 1
b110 .
b11100110110100001101111011101010110110001100100001000000111001001100101011011010110000101101001011011100010000001111010011001010111001001101111001000000110000101100110011101000110010101110010001000000111011101110010011010010111010001100101 :
b10010001101000101011001111000 9
b0 8
b1 7
b0 6
#156000
b10010001101000101011001111000 "
b10010001101000101011001111000 4
b1 '
b1 1
b111 .
b100010001110101011000010110110000100000011100100110010101100001011001000010000001110011011000010110110101100101001000000111001001100101011001110110100101110011011101000110010101110010 :
b10010001101000101011001111000 8
b1 6
b110 -
#157000
1)
b10000111011001010100001100100001 %
b10000111011001010100001100100001 0
b11 $
b11 /
b10000111011001010100001100100001 <
b11 ;
b111 -
#160000
0#
#165000
1#
#167000
0)
#170000
0#
#175000
1#
#177000
b11011110101011011011111011101111 !
b11011110101011011011111011101111 3
b10000111011001010100001100100001 "
b10000111011001010100001100100001 4
b10 (
b10 2
b11 '
b11 1
b1000 .
b100100101101101011011010110010101100100011010010110000101110100011001010010000001110010011001010110000101100100001000000110000101100110011101000110010101110010001000000111011101110010011010010111010001100101 :
b11011110101011011011111011101111 9
b10000111011001010100001100100001 8
b10 7
b11 6
#178000
b10101011110011011110111100000000 %
b10101011110011011110111100000000 0
b100 $
b100 /
b1000 -
#180000
0#
#185000
b0 !
b0 3
b0 "
b0 4
b0 (
b0 2
b100 '
b100 1
b1001 .
b11100110110000101100010011011000110010101100100001000000010110100100000011110000011010000100000011100110110100001101111011101010110110001100100001000000111001001100101011011010110000101101001011011100010000001111010011001010111001001101111 :
b0 9
b0 8
b0 7
b100 6
1#
#186000
1)
b10001000100010001000100010001 %
b10001000100010001000100010001 0
b1 $
b1 /
b10001000100010001000100010001 <
b1 ;
b1001 -
#190000
0#
#195000
1#
#196000
0)
#200000
0#
#205000
1#
#206000
b11011110101011011011111011101111 !
b11011110101011011011111011101111 3
b10001000100010001000100010001 "
b10001000100010001000100010001 4
b10 (
b10 2
b1 '
b1 1
b1010 .
b10011110111011001100101011100100111011101110010011010010111010001100101001000000111100000110001001000000111011101101001011101000110100000100000011011100110010101110111001000000111011001100001011011000111010101100101 :
b11011110101011011011111011101111 9
b10001000100010001000100010001 8
b10 7
b1 6
#207000
1)
b10000000000000000000000000001 %
b10000000000000000000000000001 0
b10000000000000000000000000001 <
b1 +
b1010 -
#210000
0#
#215000
b10000000000000000000000000001 "
b10000000000000000000000000001 4
1#
#217000
0)
#220000
0#
#225000
1#
#227000
1)
b10000000000000000000000000010 %
b10000000000000000000000000010 0
b10 $
b10 /
b10000000000000000000000000010 <
b10 ;
b10 +
#230000
0#
#235000
b10000000000000000000000000010 !
b10000000000000000000000000010 3
1#
#237000
0)
#240000
0#
#245000
1#
#247000
1)
b10000000000000000000000000011 %
b10000000000000000000000000011 0
b11 $
b11 /
b10000000000000000000000000011 <
b11 ;
b11 +
#250000
0#
#255000
1#
#257000
0)
#260000
0#
#265000
1#
#267000
1)
b10000000000000000000000000100 %
b10000000000000000000000000100 0
b100 $
b100 /
b10000000000000000000000000100 <
b100 ;
b100 +
#270000
0#
#275000
1#
#277000
0)
#280000
0#
#285000
1#
#287000
1)
b10000000000000000000000000101 %
b10000000000000000000000000101 0
b101 $
b101 /
b10000000000000000000000000101 <
b101 ;
b101 +
#290000
0#
#295000
1#
#297000
0)
#300000
0#
#305000
1#
#307000
1)
b10000000000000000000000000110 %
b10000000000000000000000000110 0
b110 $
b110 /
b10000000000000000000000000110 <
b110 ;
b110 +
#310000
0#
#315000
1#
#317000
0)
#320000
0#
#325000
1#
#327000
1)
b10000000000000000000000000111 %
b10000000000000000000000000111 0
b111 $
b111 /
b10000000000000000000000000111 <
b111 ;
b111 +
#330000
0#
#335000
1#
#337000
0)
#340000
0#
#345000
1#
#347000
1)
b10000000000000000000000001000 %
b10000000000000000000000001000 0
b1000 $
b1000 /
b10000000000000000000000001000 <
b1000 ;
b1000 +
#350000
0#
#355000
1#
#357000
0)
#360000
0#
#365000
1#
#367000
1)
b10000000000000000000000001001 %
b10000000000000000000000001001 0
b1001 $
b1001 /
b10000000000000000000000001001 <
b1001 ;
b1001 +
#370000
0#
#375000
1#
#377000
0)
#380000
0#
#385000
1#
#387000
1)
b10000000000000000000000001010 %
b10000000000000000000000001010 0
b1010 $
b1010 /
b10000000000000000000000001010 <
b1010 ;
b1010 +
#390000
0#
#395000
1#
#397000
0)
#400000
0#
#405000
1#
#407000
1)
b10000000000000000000000001011 %
b10000000000000000000000001011 0
b1011 $
b1011 /
b10000000000000000000000001011 <
b1011 ;
b1011 +
#410000
0#
#415000
1#
#417000
0)
#420000
0#
#425000
1#
#427000
1)
b10000000000000000000000001100 %
b10000000000000000000000001100 0
b1100 $
b1100 /
b10000000000000000000000001100 <
b1100 ;
b1100 +
#430000
0#
#435000
1#
#437000
0)
#440000
0#
#445000
1#
#447000
1)
b10000000000000000000000001101 %
b10000000000000000000000001101 0
b1101 $
b1101 /
b10000000000000000000000001101 <
b1101 ;
b1101 +
#450000
0#
#455000
1#
#457000
0)
#460000
0#
#465000
1#
#467000
1)
b10000000000000000000000001110 %
b10000000000000000000000001110 0
b1110 $
b1110 /
b10000000000000000000000001110 <
b1110 ;
b1110 +
#470000
0#
#475000
1#
#477000
0)
#480000
0#
#485000
1#
#487000
1)
b10000000000000000000000001111 %
b10000000000000000000000001111 0
b1111 $
b1111 /
b10000000000000000000000001111 <
b1111 ;
b1111 +
#490000
0#
#495000
1#
#497000
0)
#500000
0#
#505000
1#
#507000
1)
b10000000000000000000000010000 %
b10000000000000000000000010000 0
b10000 $
b10000 /
b10000000000000000000000010000 <
b10000 ;
b10000 +
#510000
0#
#515000
1#
#517000
0)
#520000
0#
#525000
1#
#527000
1)
b10000000000000000000000010001 %
b10000000000000000000000010001 0
b10001 $
b10001 /
b10000000000000000000000010001 <
b10001 ;
b10001 +
#530000
0#
#535000
1#
#537000
0)
#540000
0#
#545000
1#
#547000
1)
b10000000000000000000000010010 %
b10000000000000000000000010010 0
b10010 $
b10010 /
b10000000000000000000000010010 <
b10010 ;
b10010 +
#550000
0#
#555000
1#
#557000
0)
#560000
0#
#565000
1#
#567000
1)
b10000000000000000000000010011 %
b10000000000000000000000010011 0
b10011 $
b10011 /
b10000000000000000000000010011 <
b10011 ;
b10011 +
#570000
0#
#575000
1#
#577000
0)
#580000
0#
#585000
1#
#587000
1)
b10000000000000000000000010100 %
b10000000000000000000000010100 0
b10100 $
b10100 /
b10000000000000000000000010100 <
b10100 ;
b10100 +
#590000
0#
#595000
1#
#597000
0)
#600000
0#
#605000
1#
#607000
1)
b10000000000000000000000010101 %
b10000000000000000000000010101 0
b10101 $
b10101 /
b10000000000000000000000010101 <
b10101 ;
b10101 +
#610000
0#
#615000
1#
#617000
0)
#620000
0#
#625000
1#
#627000
1)
b10000000000000000000000010110 %
b10000000000000000000000010110 0
b10110 $
b10110 /
b10000000000000000000000010110 <
b10110 ;
b10110 +
#630000
0#
#635000
1#
#637000
0)
#640000
0#
#645000
1#
#647000
1)
b10000000000000000000000010111 %
b10000000000000000000000010111 0
b10111 $
b10111 /
b10000000000000000000000010111 <
b10111 ;
b10111 +
#650000
0#
#655000
1#
#657000
0)
#660000
0#
#665000
1#
#667000
1)
b10000000000000000000000011000 %
b10000000000000000000000011000 0
b11000 $
b11000 /
b10000000000000000000000011000 <
b11000 ;
b11000 +
#670000
0#
#675000
1#
#677000
0)
#680000
0#
#685000
1#
#687000
1)
b10000000000000000000000011001 %
b10000000000000000000000011001 0
b11001 $
b11001 /
b10000000000000000000000011001 <
b11001 ;
b11001 +
#690000
0#
#695000
1#
#697000
0)
#700000
0#
#705000
1#
#707000
1)
b10000000000000000000000011010 %
b10000000000000000000000011010 0
b11010 $
b11010 /
b10000000000000000000000011010 <
b11010 ;
b11010 +
#710000
0#
#715000
1#
#717000
0)
#720000
0#
#725000
1#
#727000
1)
b10000000000000000000000011011 %
b10000000000000000000000011011 0
b11011 $
b11011 /
b10000000000000000000000011011 <
b11011 ;
b11011 +
#730000
0#
#735000
1#
#737000
0)
#740000
0#
#745000
1#
#747000
1)
b10000000000000000000000011100 %
b10000000000000000000000011100 0
b11100 $
b11100 /
b10000000000000000000000011100 <
b11100 ;
b11100 +
#750000
0#
#755000
1#
#757000
0)
#760000
0#
#765000
1#
#767000
1)
b10000000000000000000000011101 %
b10000000000000000000000011101 0
b11101 $
b11101 /
b10000000000000000000000011101 <
b11101 ;
b11101 +
#770000
0#
#775000
1#
#777000
0)
#780000
0#
#785000
1#
#787000
1)
b10000000000000000000000011110 %
b10000000000000000000000011110 0
b11110 $
b11110 /
b10000000000000000000000011110 <
b11110 ;
b11110 +
#790000
0#
#795000
1#
#797000
0)
#800000
0#
#805000
1#
#807000
1)
b10000000000000000000000011111 %
b10000000000000000000000011111 0
b11111 $
b11111 /
b10000000000000000000000011111 <
b11111 ;
b11111 +
#810000
0#
#815000
1#
#817000
0)
#820000
0#
#825000
1#
#827000
b0 !
b0 3
b0 (
b0 2
b1 ,
b0 *
b100000 +
#828000
b10000000000000000000000000010 "
b10000000000000000000000000010 4
b10 '
b10 1
b10 ,
#829000
b10000000000000000000000000011 "
b10000000000000000000000000011 4
b11 '
b11 1
b11 ,
#830000
b10000000000000000000000000100 "
b10000000000000000000000000100 4
b100 '
b100 1
b100 ,
0#
#831000
b10000000000000000000000000101 "
b10000000000000000000000000101 4
b101 '
b101 1
b101 ,
#832000
b10000000000000000000000000110 "
b10000000000000000000000000110 4
b110 '
b110 1
b110 ,
#833000
b10000000000000000000000000111 "
b10000000000000000000000000111 4
b111 '
b111 1
b111 ,
#834000
b10000000000000000000000001000 "
b10000000000000000000000001000 4
b1000 '
b1000 1
b1000 ,
#835000
b10000000000000000000000001001 "
b10000000000000000000000001001 4
b1001 '
b1001 1
b1001 ,
1#
#836000
b10000000000000000000000001010 "
b10000000000000000000000001010 4
b1010 '
b1010 1
b1010 ,
#837000
b10000000000000000000000001011 "
b10000000000000000000000001011 4
b1011 '
b1011 1
b1011 ,
#838000
b10000000000000000000000001100 "
b10000000000000000000000001100 4
b1100 '
b1100 1
b1100 ,
#839000
b10000000000000000000000001101 "
b10000000000000000000000001101 4
b1101 '
b1101 1
b1101 ,
#840000
b10000000000000000000000001110 "
b10000000000000000000000001110 4
b1110 '
b1110 1
b1110 ,
0#
#841000
b10000000000000000000000001111 "
b10000000000000000000000001111 4
b1111 '
b1111 1
b1111 ,
#842000
b10000000000000000000000010000 "
b10000000000000000000000010000 4
b10000 '
b10000 1
b10000 ,
#843000
b10000000000000000000000010001 "
b10000000000000000000000010001 4
b10001 '
b10001 1
b10001 ,
#844000
b10000000000000000000000010010 "
b10000000000000000000000010010 4
b10010 '
b10010 1
b10010 ,
#845000
b10000000000000000000000010011 "
b10000000000000000000000010011 4
b10011 '
b10011 1
b10011 ,
1#
#846000
b10000000000000000000000010100 "
b10000000000000000000000010100 4
b10100 '
b10100 1
b10100 ,
#847000
b10000000000000000000000010101 "
b10000000000000000000000010101 4
b10101 '
b10101 1
b10101 ,
#848000
b10000000000000000000000010110 "
b10000000000000000000000010110 4
b10110 '
b10110 1
b10110 ,
#849000
b10000000000000000000000010111 "
b10000000000000000000000010111 4
b10111 '
b10111 1
b10111 ,
#850000
b10000000000000000000000011000 "
b10000000000000000000000011000 4
b11000 '
b11000 1
b11000 ,
0#
#851000
b10000000000000000000000011001 "
b10000000000000000000000011001 4
b11001 '
b11001 1
b11001 ,
#852000
b10000000000000000000000011010 "
b10000000000000000000000011010 4
b11010 '
b11010 1
b11010 ,
#853000
b10000000000000000000000011011 "
b10000000000000000000000011011 4
b11011 '
b11011 1
b11011 ,
#854000
b10000000000000000000000011100 "
b10000000000000000000000011100 4
b11100 '
b11100 1
b11100 ,
#855000
b10000000000000000000000011101 "
b10000000000000000000000011101 4
b11101 '
b11101 1
b11101 ,
1#
#856000
b10000000000000000000000011110 "
b10000000000000000000000011110 4
b11110 '
b11110 1
b11110 ,
#857000
b10000000000000000000000011111 "
b10000000000000000000000011111 4
b11111 '
b11111 1
b11111 ,
#858000
b1011 -
b1011 .
b100000 ,
